aws_cli_mcp_server/__init__.py
aws_cli_mcp_server/aws_cli.py
aws_cli_mcp_server/server.py
aws_cli_mcp_server-1.1.0.dist-info/METADATA
aws_cli_mcp_server-1.1.0.dist-info/WHEEL
aws_cli_mcp_server-1.1.0.dist-info/entry_points.txt
aws_cli_mcp_server-1.1.0.dist-info/RECORD
