Metadata-Version: 2.4
Name: aws-cli-mcp-server
Version: 1.1.0
Summary: A simple implementation of an AWS CLI MCP server with read/write tools for executing AWS CLI commands
Requires-Python: >=3.9
Requires-Dist: fastmcp>=2.7.1
